LICENSE.txt
MANIFEST.in
README.md
setup.cfg
setup.py
pyTrivialFTP/__init__.py
pyTrivialFTP/__main__.py
pyTrivialFTP/pyTrivialFTP.py
pyTrivialFTP.egg-info/PKG-INFO
pyTrivialFTP.egg-info/SOURCES.txt
pyTrivialFTP.egg-info/dependency_links.txt
pyTrivialFTP.egg-info/entry_points.txt
pyTrivialFTP.egg-info/top_level.txt