Metadata-Version: 1.0
Name: pyTrivialFTP
Version: 0.3.0
Summary: The poor man's API for accessing data on a remote FTP repository
Home-page: https://github.com/robertoreale/pyTrivialFTP
Author: Roberto Reale
Author-email: rober.reale@gmail.com
License: UNKNOWN
Keywords: FTP
Platform: UNKNOWN
